{
  "main": {
    "id": "5324373015726ba8",
    "type": "split",
    "children": [
      {
        "id": "846d63ff8d1de99d",
        "type": "tabs",
        "children": [
          {
            "id": "8ab39a229bef20ac",
            "type": "leaf",
            "state": {
              "type": "markdown",
              "state": {
                "file": "Intake/Dv test.md",
                "mode": "source",
                "source": false,
                "backlinks": false
              },
              "icon": "lucide-file",
              "title": "Dv test"
            }
          }
        ]
      }
    ],
    "direction": "vertical"
  },
  "left": {
    "id": "33d8e5745463cd8f",
    "type": "mobile-drawer",
    "children": [
      {
        "id": "fb931198a1134d77",
        "type": "leaf",
        "state": {
          "type": "file-explorer",
          "state": {
            "sortOrder": "alphabetical",
            "autoReveal": false
          },
          "icon": "lucide-folder-closed",
          "title": "Files"
        }
      },
      {
        "id": "7fa584d55f742b5f",
        "type": "leaf",
        "state": {
          "type": "search",
          "state": {
            "query": "",
            "matchingCase": false,
            "explainSearch": false,
            "collapseAll": false,
            "extraContext": false,
            "sortOrder": "alphabetical"
          },
          "icon": "lucide-search",
          "title": "Search"
        }
      },
      {
        "id": "eec8b1df2c587130",
        "type": "leaf",
        "state": {
          "type": "tag",
          "state": {
            "sortOrder": "frequency",
            "useHierarchy": true,
            "showSearch": false,
            "searchQuery": ""
          },
          "icon": "lucide-tags",
          "title": "Tags"
        }
      },
      {
        "id": "31ae95011f1c183e",
        "type": "leaf",
        "state": {
          "type": "all-properties",
          "state": {
            "sortOrder": "frequency",
            "showSearch": false,
            "searchQuery": ""
          },
          "icon": "lucide-archive",
          "title": "All properties"
        }
      },
      {
        "id": "bdabf3fbebcce2af",
        "type": "leaf",
        "state": {
          "type": "bookmarks",
          "state": {},
          "icon": "lucide-bookmark",
          "title": "Bookmarks"
        }
      }
    ],
    "currentTab": 0
  },
  "right": {
    "id": "64b8f46be6615f3a",
    "type": "mobile-drawer",
    "children": [
      {
        "id": "50b56f7af5d97df3",
        "type": "leaf",
        "state": {
          "type": "backlink",
          "state": {
            "file": "Intake/Dv test.md",
            "collapseAll": false,
            "extraContext": false,
            "sortOrder": "alphabetical",
            "showSearch": true,
            "searchQuery": "",
            "backlinkCollapsed": false,
            "unlinkedCollapsed": true
          },
          "icon": "links-coming-in",
          "title": "Backlinks"
        }
      },
      {
        "id": "f2d796ed93349a42",
        "type": "leaf",
        "state": {
          "type": "outgoing-link",
          "state": {
            "file": "Intake/Dv test.md",
            "linksCollapsed": false,
            "unlinkedCollapsed": true
          },
          "icon": "links-going-out",
          "title": "Outgoing links"
        }
      },
      {
        "id": "983b131bc25ddacf",
        "type": "leaf",
        "state": {
          "type": "outline",
          "state": {
            "file": "Intake/Dv test.md",
            "followCursor": false,
            "showSearch": false,
            "searchQuery": ""
          },
          "icon": "lucide-list",
          "title": "Outline"
        }
      },
      {
        "id": "5b932ab6c4f9b716",
        "type": "leaf",
        "state": {
          "type": "calendar",
          "state": {},
          "icon": "calendar-with-checkmark",
          "title": "Calendar"
        }
      },
      {
        "id": "bd2e721bdc6910a7",
        "type": "leaf",
        "state": {
          "type": "footnotes",
          "state": {
            "file": "Slurped Pages/The Quest to Find the Longest-Running Simple Computer Program.md"
          },
          "icon": "lucide-file-signature",
          "title": "Footnotes"
        }
      },
      {
        "id": "a75d134e6a9c702f",
        "type": "leaf",
        "state": {
          "type": "empty",
          "state": {},
          "icon": "lucide-file",
          "title": "New tab"
        }
      },
      {
        "id": "98d46072236583f9",
        "type": "leaf",
        "state": {
          "type": "netClip_workspace_webview",
          "state": {},
          "icon": "globe",
          "title": "Web View"
        }
      }
    ],
    "currentTab": 5
  },
  "left-ribbon": {
    "hiddenItems": {
      "command-palette:Open command palette": false,
      "bases:Create new base": false,
      "switcher:Open quick switcher": false,
      "templates:Insert template": true,
      "zk-prefixer:Create new unique note": false,
      "graph:Open graph view": false,
      "markdown-importer:Open format converter": false,
      "table-editor-obsidian:Advanced Tables Toolbar": false,
      "quickadd:QuickAdd": false,
      "cmdr:Open settings": false,
      "cmdr:Open another vault": false,
      "cmdr:Slurp Page": false,
      "cmdr:Ace Code Editor: Open CSS snippet manager": false,
      "cmdr:Snippets Manager: Search Snippets": false,
      "quicklink:Auto link scan": false,
      "ace-code-editor:Open CSS snippet manager": false,
      "omnisearch:Omnisearch": false,
      "templater-obsidian:Templater": false,
      "obsidian42-brat:BRAT": false,
      "callout-manager:Insert Callout": false,
      "obsidian-kanban:Create new board": false,
      "net-clip:NetClip": false,
      "tag-index:Open tag index": false,
      "widgets:Add widget": false,
      "darlal-switcher-plus:Open in Headings Mode": false,
      "darlal-switcher-plus:Open Symbols for the active editor": false
    }
  },
  "active": "fb931198a1134d77",
  "lastOpenFiles": [
    "Templates",
    "Untitled Kanban.md",
    "meta_bind_guide.md",
    "Template - Book.md",
    "obsidian_dashboard_queries.md",
    "Theme Primary, Specifics.md",
    "Notes, Excel.md",
    "Idex.md",
    "Intake/Luxon, JavaScript Date & Time Wrapper.md",
    "temps/Core Idea.md",
    "temps/Project MOC Template.md",
    "temps/Project Note Template.md",
    "Intake/LINKs.md",
    "temps/Dashboard.md",
    "Termux-Command-Handbook/chapter_04.md",
    "Termux-Command-Handbook/chapter_03.md",
    "Termux-Command-Handbook/chapter_02.md",
    "Intake/JavaScript Libraries.md",
    "Ref_Sheets/The Ultimate Guide to Termux Commands.md",
    "Termux-Command-Handbook/Chapter1.md",
    "Termux-Command-Handbook/chapter_01.md",
    "Ref_Sheets",
    "temps/Experiment Template.md",
    "temps/Course MOC.md",
    "Intake/Bookmark Ninja Mobile Share.md",
    "temps/Protocol MOC.md",
    "temps/Lab Inventory MOC.md",
    "temps",
    "NetClip/Mind",
    "NetClip/CS",
    "NetClip/Design",
    "NetClip/Tech",
    "NetClip/Research",
    "NetClip/Articles",
    "NetClip",
    "ExTyp_stylesettings.json",
    "typeface anatomy.jpg",
    "Anatomy of Typeface.jpg",
    "digi5d.png",
    "AOR Map -Combatant Commands.png",
    "_bin_/callout-tabbed.jpg",
    "@_code/_&-(aux)-devicons/bin/devicons ref cheatsheet.png"
  ]
}